setup.py
fabric_threadsafe/__init__.py
fabric_threadsafe/patch.py
fabric_threadsafe.egg-info/PKG-INFO
fabric_threadsafe.egg-info/SOURCES.txt
fabric_threadsafe.egg-info/dependency_links.txt
fabric_threadsafe.egg-info/top_level.txt
fabric_threadsafe.egg-info/zip-safe