Metadata-Version: 1.0
Name: fabric-threadsafe
Version: 0.1.0
Summary: Monkeypatch script to make Fabric thread-safe
Home-page: https://github.com/bancek/fabric-threadsafe
Author: Luka Zakrajsek
Author-email: luka@bancek.net
License: Apache
Platform: UNKNOWN
Classifier: Intended Audience :: Developers
Classifier: License :: OSI Approved :: Apache Software License
Classifier: Operating System :: OS Independent
Classifier: Programming Language :: Python
Classifier: Topic :: Software Development :: Libraries :: Python Modules
Classifier: Topic :: System :: Networking
